structural_starterkit/__init__.py
structural_starterkit/__main__.py
structural_starterkit/sectionproperties_test.py
structural_starterkit-0.5.0.dist-info/entry_points.txt
structural_starterkit-0.5.0.dist-info/licenses/LICENSE
structural_starterkit-0.5.0.dist-info/WHEEL
structural_starterkit-0.5.0.dist-info/METADATA
structural_starterkit-0.5.0.dist-info/RECORD
